tbase_page/__init__.py
tbase_page/admin.py
tbase_page/apps.py
tbase_page/models.py
tbase_page/tests.py
tbase_page/urls.py
tbase_page/views.py
tbase_page/migrations/0001_initial.py
tbase_page/migrations/0001_initial.py:Zone.Identifier
tbase_page/migrations/0002_auto_20230421_1307.py
tbase_page/migrations/0002_auto_20230421_1307.py:Zone.Identifier
tbase_page/migrations/0003_basepage_robots_txt.py
tbase_page/migrations/__init__.py
tbase_page/migrations/__init__.py:Zone.Identifier
tbase_page/templates/about_us.html
tbase_page/templates/about_us.html:Zone.Identifier
tbase_page/templates/ads_txt.html
tbase_page/templates/contact_us.html
tbase_page/templates/contact_us.html:Zone.Identifier
tbase_page/templates/home.html
tbase_page/templates/home.html:Zone.Identifier
tbase_page/templates/privacy_policy.html
tbase_page/templates/privacy_policy.html:Zone.Identifier
tbase_page/templates/robots_txt.html
tbase_page/templates/terms_and_conditions.html
tbase_page/templates/terms_and_conditions.html:Zone.Identifier
django_tbase_page-2024.6.1617184706.dist-info/METADATA
django_tbase_page-2024.6.1617184706.dist-info/WHEEL
django_tbase_page-2024.6.1617184706.dist-info/top_level.txt
django_tbase_page-2024.6.1617184706.dist-info/RECORD
