Metadata-Version: 2.1
Name: django-tbase-page
Version: 2024.6.1617184706
Summary: Terry django base post ,
Home-page: https://terrychanorg.jetbrains.space/p/django-expand/repositories/tbase_page/files/README.md
Author: Terry Chan
Author-email: napoler2008@gmail.com
Requires-Dist: django-tbase-theme-tailwind ==2023.7.316883187
Requires-Dist: martor ==1.6.19
